README.rst
setup.py
rblk/__init__.py
rblk/txt.py
rblk.egg-info/PKG-INFO
rblk.egg-info/SOURCES.txt
rblk.egg-info/dependency_links.txt
rblk.egg-info/top_level.txt
rblk/ele/__init__.py
rblk/ele/arr.py
rblk/ele/txt.py
rblk/mat/__init__.py
rblk/mat/engine.py
rblk/mat/pbreadth.py
rblk/mat/tag.py
rblk/scanner/__init__.py
rblk/scanner/arr.py
rblk/scanner/txt.py
rblk/tag/__init__.py
rblk/tag/arr.py
rblk/tag/engine.py
rblk/tag/txt.py
rblk/utils/__init__.py
rblk/utils/fsm.py
rblk/utils/ltdict.py