Metadata-Version: 1.1
Name: rblk
Version: 0.5
Summary: recursive match nested brackets
Home-page: https://github.com/ihgazni2/rblk
Author: dapeli
Author-email: terryinzaghi@163.com
License: MIT
Platform: UNKNOWN
Classifier: Environment :: Console
Classifier: Environment :: Web Environment
Classifier: Intended Audience :: End Users/Desktop
Classifier: Intended Audience :: Developers
Classifier: Intended Audience :: System Administrators
Classifier: Programming Language :: Python
